MANIFEST.in
README.rst
setup.py
ovrsdk/__init__.py
ovrsdk/ovrsdk.py
ovrsdk/linux/__init__.py
ovrsdk/linux/libovr.so
ovrsdk/linux/wrapper.py
ovrsdk/windows/__init__.py
ovrsdk/windows/libovr.dll
ovrsdk/windows/wrapper.py
python_ovrsdk.egg-info/PKG-INFO
python_ovrsdk.egg-info/SOURCES.txt
python_ovrsdk.egg-info/dependency_links.txt
python_ovrsdk.egg-info/top_level.txt
test/test.py