Metadata-Version: 1.0
Name: python-ovrsdk
Version: 0.3.2.2
Summary: Python wrapper for Oculus VR SDK.
Home-page: https://github.com/wwwtyro/python-ovrsdk
Author: Rye Terrell
Author-email: wwwtyro@gmail.com
License: UNKNOWN
Platform: UNKNOWN
